Workbook

Sheet Assumptions
A1: MVR DIGITAL 2026 - ASSUMPTIONS & INPUTS
A3: CLIENT REVENUE ASSUMPTIONS
A4: Client | B4: Base Retainer | C4: % of Ad Spend | D4: Creative Hrs/Mo | E4: Creative Rate | F4: Email Fee/Mo | G4: Notes
A5: Peddle | B5: 0 | C5: 0.055 | D5: 80 | E5: 130 | F5: 0 | G5: Creative hours billable at $130/hr
A6: Alo | B6: 0 | C6: 0 | D6: 20 | E6: 250 | F6: 0 | G6: Creative services only
A7: Sunflow | B7: 0 | C7: 0.07 | D7: 0 | E7: 0 | F7: 0 | G7: +$450 Blotout
A8: Kaspar & Lugay | B8: 1000 | C8: 0.05 | D8: 0 | E8: 0 | F8: 0 | G8: 5 creative hrs included
A9: Wrensilva | B9: 4000 | C9: 0.07 | D9: 0 | E9: 0 | F9: 2000 | G9: $2K email + 20 creative hrs included
A10: Sonsie | B10: 4000 | C10: 0.07 | D10: 0 | E10: 0 | F10: 0 | G10: Email included, 15 creative hrs included
A13: MONTHLY COST ASSUMPTIONS
A14: Category | B14: Monthly Amount | C14: Notes
A15: Salaries & Wages | B15: 20615 | C15: Based on 2025 avg
A16: Employer Taxes | B16: 1674 | C16: Based on 2025 avg
A17: Employee Benefits | B17: 1575 | C17: Based on 2025 avg
A18: Contract Labor | B18: 35839 | C18: Based on 2025 avg
A19: Software & Apps | B19: 4829 | C19: Based on 2025 avg
A20: Insurance | B20: 2962 | C20: Based on 2025 avg
A21: Consulting/Accounting | B21: 2000 | C21: Based on 2025 avg
A22: Travel | B22: 1526 | C22: Based on 2025 avg
A23: Advertising/Marketing | B23: 1088 | C23: Based on 2025 avg
A24: Other (office, meals, fees) | B24: 1500 | C24: Misc expenses

Sheet Ad Spend Input
A1: MONTHLY AD SPEND BY CLIENT
A3: Client | B3: Jan | C3: Feb | D3: Mar | E3: Apr | F3: May | G3: Jun | H3: Jul | I3: Aug | J3: Sep | K3: Oct | L3: Nov | M3: Dec | N3: Total
A4: Peddle | B4: 700000 | C4: 720000 | D4: 750000 | E4: 780000 | F4: 800000 | G4: 850000 | H4: 900000 | I4: 950000 | J4: 900000 | K4: 850000 | L4: 900000 | M4: 950000 | N4: =SUM(B4:M4) -> 10050000
A5: Alo | B5: 0 | C5: 0 | D5: 0 | E5: 0 | F5: 0 | G5: 0 | H5: 0 | I5: 0 | J5: 0 | K5: 0 | L5: 0 | M5: 0 | N5: =SUM(B5:M5) -> 0
A6: Sunflow | B6: 20000 | C6: 25000 | D6: 40000 | E6: 60000 | F6: 80000 | G6: 100000 | H6: 120000 | I6: 100000 | J6: 60000 | K6: 30000 | L6: 40000 | M6: 80000 | N6: =SUM(B6:M6) -> 755000
A7: Kaspar & Lugay | B7: 80000 | C7: 85000 | D7: 90000 | E7: 95000 | F7: 100000 | G7: 100000 | H7: 100000 | I7: 100000 | J7: 100000 | K7: 95000 | L7: 100000 | M7: 105000 | N7: =SUM(B7:M7) -> 1150000
A8: Wrensilva | B8: 40000 | C8: 45000 | D8: 50000 | E8: 55000 | F8: 60000 | G8: 70000 | H8: 80000 | I8: 90000 | J8: 100000 | K8: 120000 | L8: 130000 | M8: 150000 | N8: =SUM(B8:M8) -> 990000
A9: Sonsie | B9: 30000 | C9: 35000 | D9: 40000 | E9: 45000 | F9: 50000 | G9: 60000 | H9: 80000 | I9: 70000 | J9: 60000 | K9: 70000 | L9: 80000 | M9: 100000 | N9: =SUM(B9:M9) -> 720000
A10: TOTAL AD SPEND | B10: =SUM(B4:B9) -> 870000 | C10: =SUM(C4:C9) -> 910000 | D10: =SUM(D4:D9) -> 970000 | E10: =SUM(E4:E9) -> 1035000 | F10: =SUM(F4:F9) -> 1090000 | G10: =SUM(G4:G9) -> 1180000 | H10: =SUM(H4:H9) -> 1280000 | I10: =SUM(I4:I9) -> 1310000 | ... N10: =SUM(N4:N9) -> 13665000

Sheet Revenue Projection
A1: MONTHLY REVENUE PROJECTION
A3: Client | B3: Jan | C3: Feb | D3: Mar | E3: Apr | F3: May | G3: Jun | H3: Jul | I3: Aug | J3: Sep | K3: Oct | L3: Nov | M3: Dec | N3: Total
A4: Peddle | B4: =Assumptions!$B$5+('Ad Spend Input'!B4*Assumptions!$C$5)+(Assumptions!$D$5*Assumptions!$E$5)+Assumptions!$F$5 -> 48900 | C4: =Assumptions!$B$5+('Ad Spend Input'!C4*Assumptions!$C$5)+(Assumptions!$D$5*Assumptions!$E$5)+Assumptions!$F$5 -> 50000 | D4: =Assumptions!$B$5+('Ad Spend Input'!D4*Assumptions!$C$5)+(Assumptions!$D$5*Assumptions!$E$5)+Assumptions!$F$5 -> 51650 | E4: =Assumptions!$B$5+('Ad Spend Input'!E4*Assumptions!$C$5)+(Assumptions!$D$5*Assumptions!$E$5)+Assumptions!$F$5 -> 53300 | F4: =Assumptions!$B$5+('Ad Spend Input'!F4*Assumptions!$C$5)+(Assumptions!$D$5*Assumptions!$E$5)+Assumptions!$F$5 -> 54400 | G4: =Assumptions!$B$5+('Ad Spend Input'!G4*Assumptions!$C$5)+(Assumptions!$D$5*Assumptions!$E$5)+Assumptions!$F$5 -> 57150 | H4: =Assumptions!$B$5+('Ad Spend Input'!H4*Assumptions!$C$5)+(Assumptions!$D$5*Assumptions!$E$5)+Assumptions!$F$5 -> 59900 | I4: =Assumptions!$B$5+('Ad Spend Input'!I4*Assumptions!$C$5)+(Assumptions!$D$5*Assumptions!$E$5)+Assumptions!$F$5 -> 62650 | ... M4: =Assumptions!$B$5+('Ad Spend Input'!M4*Assumptions!$C$5)+(Assumptions!$D$5*Assumptions!$E$5)+Assumptions!$F$5 -> 62650 | N4: =SUM(B4:M4) -> 677550
A5: Alo | B5: =Assumptions!$B$6+('Ad Spend Input'!B5*Assumptions!$C$6)+(Assumptions!$D$6*Assumptions!$E$6)+Assumptions!$F$6 -> 5000 | C5: =Assumptions!$B$6+('Ad Spend Input'!C5*Assumptions!$C$6)+(Assumptions!$D$6*Assumptions!$E$6)+Assumptions!$F$6 -> 5000 | D5: =Assumptions!$B$6+('Ad Spend Input'!D5*Assumptions!$C$6)+(Assumptions!$D$6*Assumptions!$E$6)+Assumptions!$F$6 -> 5000 | E5: =Assumptions!$B$6+('Ad Spend Input'!E5*Assumptions!$C$6)+(Assumptions!$D$6*Assumptions!$E$6)+Assumptions!$F$6 -> 5000 | F5: =Assumptions!$B$6+('Ad Spend Input'!F5*Assumptions!$C$6)+(Assumptions!$D$6*Assumptions!$E$6)+Assumptions!$F$6 -> 5000 | G5: =Assumptions!$B$6+('Ad Spend Input'!G5*Assumptions!$C$6)+(Assumptions!$D$6*Assumptions!$E$6)+Assumptions!$F$6 -> 5000 | H5: =Assumptions!$B$6+('Ad Spend Input'!H5*Assumptions!$C$6)+(Assumptions!$D$6*Assumptions!$E$6)+Assumptions!$F$6 -> 5000 | I5: =Assumptions!$B$6+('Ad Spend Input'!I5*Assumptions!$C$6)+(Assumptions!$D$6*Assumptions!$E$6)+Assumptions!$F$6 -> 5000 | ... M5: =Assumptions!$B$6+('Ad Spend Input'!M5*Assumptions!$C$6)+(Assumptions!$D$6*Assumptions!$E$6)+Assumptions!$F$6 -> 5000 | N5: =SUM(B5:M5) -> 60000
A6: Sunflow | B6: =Assumptions!$B$7+('Ad Spend Input'!B6*Assumptions!$C$7)+(Assumptions!$D$7*Assumptions!$E$7)+Assumptions!$F$7 -> 1400 | C6: =Assumptions!$B$7+('Ad Spend Input'!C6*Assumptions!$C$7)+(Assumptions!$D$7*Assumptions!$E$7)+Assumptions!$F$7 -> 1750 | D6: =Assumptions!$B$7+('Ad Spend Input'!D6*Assumptions!$C$7)+(Assumptions!$D$7*Assumptions!$E$7)+Assumptions!$F$7 -> 2800 | E6: =Assumptions!$B$7+('Ad Spend Input'!E6*Assumptions!$C$7)+(Assumptions!$D$7*Assumptions!$E$7)+Assumptions!$F$7 -> 4200 | F6: =Assumptions!$B$7+('Ad Spend Input'!F6*Assumptions!$C$7)+(Assumptions!$D$7*Assumptions!$E$7)+Assumptions!$F$7 -> 5600 | G6: =Assumptions!$B$7+('Ad Spend Input'!G6*Assumptions!$C$7)+(Assumptions!$D$7*Assumptions!$E$7)+Assumptions!$F$7 -> 7000 | H6: =Assumptions!$B$7+('Ad Spend Input'!H6*Assumptions!$C$7)+(Assumptions!$D$7*Assumptions!$E$7)+Assumptions!$F$7 -> 8400 | I6: =Assumptions!$B$7+('Ad Spend Input'!I6*Assumptions!$C$7)+(Assumptions!$D$7*Assumptions!$E$7)+Assumptions!$F$7 -> 7000 | ... M6: =Assumptions!$B$7+('Ad Spend Input'!M6*Assumptions!$C$7)+(Assumptions!$D$7*Assumptions!$E$7)+Assumptions!$F$7 -> 5600 | N6: =SUM(B6:M6) -> 52850
A7: Kaspar & Lugay | B7: =Assumptions!$B$8+('Ad Spend Input'!B7*Assumptions!$C$8)+(Assumptions!$D$8*Assumptions!$E$8)+Assumptions!$F$8 -> 5000 | C7: =Assumptions!$B$8+('Ad Spend Input'!C7*Assumptions!$C$8)+(Assumptions!$D$8*Assumptions!$E$8)+Assumptions!$F$8 -> 5250 | D7: =Assumptions!$B$8+('Ad Spend Input'!D7*Assumptions!$C$8)+(Assumptions!$D$8*Assumptions!$E$8)+Assumptions!$F$8 -> 5500 | E7: =Assumptions!$B$8+('Ad Spend Input'!E7*Assumptions!$C$8)+(Assumptions!$D$8*Assumptions!$E$8)+Assumptions!$F$8 -> 5750 | F7: =Assumptions!$B$8+('Ad Spend Input'!F7*Assumptions!$C$8)+(Assumptions!$D$8*Assumptions!$E$8)+Assumptions!$F$8 -> 6000 | G7: =Assumptions!$B$8+('Ad Spend Input'!G7*Assumptions!$C$8)+(Assumptions!$D$8*Assumptions!$E$8)+Assumptions!$F$8 -> 6000 | H7: =Assumptions!$B$8+('Ad Spend Input'!H7*Assumptions!$C$8)+(Assumptions!$D$8*Assumptions!$E$8)+Assumptions!$F$8 -> 6000 | I7: =Assumptions!$B$8+('Ad Spend Input'!I7*Assumptions!$C$8)+(Assumptions!$D$8*Assumptions!$E$8)+Assumptions!$F$8 -> 6000 | ... M7: =Assumptions!$B$8+('Ad Spend Input'!M7*Assumptions!$C$8)+(Assumptions!$D$8*Assumptions!$E$8)+Assumptions!$F$8 -> 6250 | N7: =SUM(B7:M7) -> 69500
A8: Wrensilva | B8: =Assumptions!$B$9+('Ad Spend Input'!B8*Assumptions!$C$9)+(Assumptions!$D$9*Assumptions!$E$9)+Assumptions!$F$9 -> 8800 | C8: =Assumptions!$B$9+('Ad Spend Input'!C8*Assumptions!$C$9)+(Assumptions!$D$9*Assumptions!$E$9)+Assumptions!$F$9 -> 9150 | D8: =Assumptions!$B$9+('Ad Spend Input'!D8*Assumptions!$C$9)+(Assumptions!$D$9*Assumptions!$E$9)+Assumptions!$F$9 -> 9500 | E8: =Assumptions!$B$9+('Ad Spend Input'!E8*Assumptions!$C$9)+(Assumptions!$D$9*Assumptions!$E$9)+Assumptions!$F$9 -> 9850 | F8: =Assumptions!$B$9+('Ad Spend Input'!F8*Assumptions!$C$9)+(Assumptions!$D$9*Assumptions!$E$9)+Assumptions!$F$9 -> 10200 | G8: =Assumptions!$B$9+('Ad Spend Input'!G8*Assumptions!$C$9)+(Assumptions!$D$9*Assumptions!$E$9)+Assumptions!$F$9 -> 10900 | H8: =Assumptions!$B$9+('Ad Spend Input'!H8*Assumptions!$C$9)+(Assumptions!$D$9*Assumptions!$E$9)+Assumptions!$F$9 -> 11600 | I8: =Assumptions!$B$9+('Ad Spend Input'!I8*Assumptions!$C$9)+(Assumptions!$D$9*Assumptions!$E$9)+Assumptions!$F$9 -> 12300 | ... M8: =Assumptions!$B$9+('Ad Spend Input'!M8*Assumptions!$C$9)+(Assumptions!$D$9*Assumptions!$E$9)+Assumptions!$F$9 -> 16500 | N8: =SUM(B8:M8) -> 141300
A9: Sonsie | B9: =Assumptions!$B$10+('Ad Spend Input'!B9*Assumptions!$C$10)+(Assumptions!$D$10*Assumptions!$E$10)+Assumptions!$F$10 -> 6100 | C9: =Assumptions!$B$10+('Ad Spend Input'!C9*Assumptions!$C$10)+(Assumptions!$D$10*Assumptions!$E$10)+Assumptions!$F$10 -> 6450 | D9: =Assumptions!$B$10+('Ad Spend Input'!D9*Assumptions!$C$10)+(Assumptions!$D$10*Assumptions!$E$10)+Assumptions!$F$10 -> 6800 | E9: =Assumptions!$B$10+('Ad Spend Input'!E9*Assumptions!$C$10)+(Assumptions!$D$10*Assumptions!$E$10)+Assumptions!$F$10 -> 7150 | F9: =Assumptions!$B$10+('Ad Spend Input'!F9*Assumptions!$C$10)+(Assumptions!$D$10*Assumptions!$E$10)+Assumptions!$F$10 -> 7500 | G9: =Assumptions!$B$10+('Ad Spend Input'!G9*Assumptions!$C$10)+(Assumptions!$D$10*Assumptions!$E$10)+Assumptions!$F$10 -> 8200 | H9: =Assumptions!$B$10+('Ad Spend Input'!H9*Assumptions!$C$10)+(Assumptions!$D$10*Assumptions!$E$10)+Assumptions!$F$10 -> 9600 | I9: =Assumptions!$B$10+('Ad Spend Input'!I9*Assumptions!$C$10)+(Assumptions!$D$10*Assumptions!$E$10)+Assumptions!$F$10 -> 8900 | ... M9: =Assumptions!$B$10+('Ad Spend Input'!M9*Assumptions!$C$10)+(Assumptions!$D$10*Assumptions!$E$10)+Assumptions!$F$10 -> 11000 | N9: =SUM(B9:M9) -> 98400
A10: TOTAL REVENUE | B10: =SUM(B4:B9) -> 75200 | C10: =SUM(C4:C9) -> 77600 | D10: =SUM(D4:D9) -> 81250 | E10: =SUM(E4:E9) -> 85250 | F10: =SUM(F4:F9) -> 88700 | G10: =SUM(G4:G9) -> 94250 | H10: =SUM(H4:H9) -> 100500 | I10: =SUM(I4:I9) -> 101850 | ... N10: =SUM(N4:N9) -> 1099600

Sheet Monthly Costs
A1: MONTHLY COST BREAKDOWN
A3: Category | B3: Jan | C3: Feb | D3: Mar | E3: Apr | F3: May | G3: Jun | H3: Jul | I3: Aug | J3: Sep | K3: Oct | L3: Nov | M3: Dec | N3: Total
A4: Salaries & Wages | B4: =Assumptions!$B$15 -> 20615 | C4: =Assumptions!$B$15 -> 20615 | D4: =Assumptions!$B$15 -> 20615 | E4: =Assumptions!$B$15 -> 20615 | F4: =Assumptions!$B$15 -> 20615 | G4: =Assumptions!$B$15 -> 20615 | H4: =Assumptions!$B$15 -> 20615 | I4: =Assumptions!$B$15 -> 20615 | ... M4: =Assumptions!$B$15 -> 20615 | N4: =SUM(B4:M4) -> 247380
A5: Employer Taxes | B5: =Assumptions!$B$16 -> 1674 | C5: =Assumptions!$B$16 -> 1674 | D5: =Assumptions!$B$16 -> 1674 | E5: =Assumptions!$B$16 -> 1674 | F5: =Assumptions!$B$16 -> 1674 | G5: =Assumptions!$B$16 -> 1674 | H5: =Assumptions!$B$16 -> 1674 | I5: =Assumptions!$B$16 -> 1674 | ... M5: =Assumptions!$B$16 -> 1674 | N5: =SUM(B5:M5) -> 20088
A6: Employee Benefits | B6: =Assumptions!$B$17 -> 1575 | C6: =Assumptions!$B$17 -> 1575 | D6: =Assumptions!$B$17 -> 1575 | E6: =Assumptions!$B$17 -> 1575 | F6: =Assumptions!$B$17 -> 1575 | G6: =Assumptions!$B$17 -> 1575 | H6: =Assumptions!$B$17 -> 1575 | I6: =Assumptions!$B$17 -> 1575 | ... M6: =Assumptions!$B$17 -> 1575 | N6: =SUM(B6:M6) -> 18900
A7: Contract Labor | B7: =Assumptions!$B$18 -> 35839 | C7: =Assumptions!$B$18 -> 35839 | D7: =Assumptions!$B$18 -> 35839 | E7: =Assumptions!$B$18 -> 35839 | F7: =Assumptions!$B$18 -> 35839 | G7: =Assumptions!$B$18 -> 35839 | H7: =Assumptions!$B$18 -> 35839 | I7: =Assumptions!$B$18 -> 35839 | ... M7: =Assumptions!$B$18 -> 35839 | N7: =SUM(B7:M7) -> 430068
A8: Software & Apps | B8: =Assumptions!$B$19 -> 4829 | C8: =Assumptions!$B$19 -> 4829 | D8: =Assumptions!$B$19 -> 4829 | E8: =Assumptions!$B$19 -> 4829 | F8: =Assumptions!$B$19 -> 4829 | G8: =Assumptions!$B$19 -> 4829 | H8: =Assumptions!$B$19 -> 4829 | I8: =Assumptions!$B$19 -> 4829 | ... M8: =Assumptions!$B$19 -> 4829 | N8: =SUM(B8:M8) -> 57948
A9: Insurance | B9: =Assumptions!$B$20 -> 2962 | C9: =Assumptions!$B$20 -> 2962 | D9: =Assumptions!$B$20 -> 2962 | E9: =Assumptions!$B$20 -> 2962 | F9: =Assumptions!$B$20 -> 2962 | G9: =Assumptions!$B$20 -> 2962 | H9: =Assumptions!$B$20 -> 2962 | I9: =Assumptions!$B$20 -> 2962 | ... M9: =Assumptions!$B$20 -> 2962 | N9: =SUM(B9:M9) -> 35544
A10: Consulting/Accounting | B10: =Assumptions!$B$21 -> 2000 | C10: =Assumptions!$B$21 -> 2000 | D10: =Assumptions!$B$21 -> 2000 | E10: =Assumptions!$B$21 -> 2000 | F10: =Assumptions!$B$21 -> 2000 | G10: =Assumptions!$B$21 -> 2000 | H10: =Assumptions!$B$21 -> 2000 | I10: =Assumptions!$B$21 -> 2000 | ... M10: =Assumptions!$B$21 -> 2000 | N10: =SUM(B10:M10) -> 24000
A11: Travel | B11: =Assumptions!$B$22 -> 1526 | C11: =Assumptions!$B$22 -> 1526 | D11: =Assumptions!$B$22 -> 1526 | E11: =Assumptions!$B$22 -> 1526 | F11: =Assumptions!$B$22 -> 1526 | G11: =Assumptions!$B$22 -> 1526 | H11: =Assumptions!$B$22 -> 1526 | I11: =Assumptions!$B$22 -> 1526 | ... M11: =Assumptions!$B$22 -> 1526 | N11: =SUM(B11:M11) -> 18312
A12: Advertising/Marketing | B12: =Assumptions!$B$23 -> 1088 | C12: =Assumptions!$B$23 -> 1088 | D12: =Assumptions!$B$23 -> 1088 | E12: =Assumptions!$B$23 -> 1088 | F12: =Assumptions!$B$23 -> 1088 | G12: =Assumptions!$B$23 -> 1088 | H12: =Assumptions!$B$23 -> 1088 | I12: =Assumptions!$B$23 -> 1088 | ... M12: =Assumptions!$B$23 -> 1088 | N12: =SUM(B12:M12) -> 13056
A13: Other (office, meals, fees) | B13: =Assumptions!$B$24 -> 1500 | C13: =Assumptions!$B$24 -> 1500 | D13: =Assumptions!$B$24 -> 1500 | E13: =Assumptions!$B$24 -> 1500 | F13: =Assumptions!$B$24 -> 1500 | G13: =Assumptions!$B$24 -> 1500 | H13: =Assumptions!$B$24 -> 1500 | I13: =Assumptions!$B$24 -> 1500 | ... M13: =Assumptions!$B$24 -> 1500 | N13: =SUM(B13:M13) -> 18000
A14: TOTAL COSTS | B14: =SUM(B4:B13) -> 73608 | C14: =SUM(C4:C13) -> 73608 | D14: =SUM(D4:D13) -> 73608 | E14: =SUM(E4:E13) -> 73608 | F14: =SUM(F4:F13) -> 73608 | G14: =SUM(G4:G13) -> 73608 | H14: =SUM(H4:H13) -> 73608 | I14: =SUM(I4:I13) -> 73608 | ... N14: =SUM(N4:N13) -> 883296

Sheet Cashflow
A1: MONTHLY CASHFLOW SUMMARY
A3: Item | B3: Jan | C3: Feb | D3: Mar | E3: Apr | F3: May | G3: Jun | H3: Jul | I3: Aug | J3: Sep | K3: Oct | L3: Nov | M3: Dec | N3: Total
A4: Total Revenue | B4: ='Revenue Projection'!B10 -> 75200 | C4: ='Revenue Projection'!C10 -> 77600 | D4: ='Revenue Projection'!D10 -> 81250 | E4: ='Revenue Projection'!E10 -> 85250 | F4: ='Revenue Projection'!F10 -> 88700 | G4: ='Revenue Projection'!G10 -> 94250 | H4: ='Revenue Projection'!H10 -> 100500 | I4: ='Revenue Projection'!I10 -> 101850 | ... N4: ='Revenue Projection'!N10 -> 1099600
A5: Total Costs | B5: ='Monthly Costs'!B14 -> 73608 | C5: ='Monthly Costs'!C14 -> 73608 | D5: ='Monthly Costs'!D14 -> 73608 | E5: ='Monthly Costs'!E14 -> 73608 | F5: ='Monthly Costs'!F14 -> 73608 | G5: ='Monthly Costs'!G14 -> 73608 | H5: ='Monthly Costs'!H14 -> 73608 | I5: ='Monthly Costs'!I14 -> 73608 | ... N5: ='Monthly Costs'!N14 -> 883296
A7: NET CASHFLOW | B7: =B4-B5 -> 1592 | C7: =C4-C5 -> 3992 | D7: =D4-D5 -> 7642 | E7: =E4-E5 -> 11642 | F7: =F4-F5 -> 15092 | G7: =G4-G5 -> 20642 | H7: =H4-H5 -> 26892 | I7: =I4-I5 -> 28242 | ... N7: =N4-N5 -> 216304
A8: Cumulative | B8: =B7 -> 1592 | C8: =B8+C7 -> 5584 | D8: =C8+D7 -> 13226 | E8: =D8+E7 -> 24868 | F8: =E8+F7 -> 39960 | G8: =F8+G7 -> 60602 | H8: =G8+H7 -> 87494 | I8: =H8+I7 -> 115736 | J8: =I8+J7 -> 138428 | ... M8: =L8+M7 -> 216304 | N8: =M8 -> 216304
A10: ANNUAL SUMMARY
A11: Total Annual Revenue | B11: ='Revenue Projection'!N10 -> 1099600
A12: Total Annual Costs | B12: ='Monthly Costs'!N14 -> 883296
A13: Annual Net Income | B13: =B11-B12 -> 216304
A14: Profit Margin | B14: =IF(B11>0,B13/B11,0) -> 0.19671153
A16: Monthly Avg Revenue | B16: =B11/12 -> 91633.333
A17: Monthly Avg Costs | B17: =B12/12 -> 73608
A18: Monthly Avg Net | B18: =B13/12 -> 18025.333
