Workbook

Sheet Dashboard
A1: MVR DIGITAL - GROWTH FINANCIAL MODEL
A2: Monthly Performance Dashboard
A3: Last Updated: | B3: =TODAY() -> 46052
A5: KEY METRICS
A7: Current Monthly Revenue | B7: =Assumptions!B6 -> 95000
A8: Monthly Expenses | B8: =Projection!N8 -> 0
A9: Net Operating Income | B9: =B7-B8 -> 95000
A10: Operating Margin | B10: =IF(B7>0,B9/B7,0) -> 1
A12: Target Monthly Revenue | B12: =Assumptions!B7 -> 150000
A13: Gap to Target | B13: =B12-B7 -> 55000
A14: New Clients Needed (at $15K avg) | B14: =ROUNDUP(B13/15000,0) -> 4
A16: REVENUE CONCENTRATION
A18: Peddle % of Revenue | B18: =Assumptions!B11/Assumptions!B6 -> 0.51578947 | C18: (Target: <40%)
A20: HIRING STATUS
A22: Account Manager | B22: =IF(Assumptions!B26="Yes","Hired","Not Hired") -> Not Hired | C22: =IF(Assumptions!B26="Yes",Assumptions!B27/12,"")
A23: Project Manager | B23: =IF(Assumptions!B29="Yes","Hired","Not Hired") -> Not Hired | C23: =IF(Assumptions!B29="Yes",Assumptions!B30/12,"")
A25: PROFITABILITY TRIGGERS
A27: Safe to Hire AM (Rev >= $110K)? | B27: =IF(B7>=110000,"YES - PROCEED","NOT YET") -> NOT YET
A28: Safe to Hire PM (Rev >= $120K)? | B28: =IF(B7>=120000,"YES - PROCEED","NOT YET") -> NOT YET
A29: At Target Margin (>=35%)? | B29: =IF(B10>=0.35,"YES","NO") -> YES
A31: SUNFLOW SEASONALITY IMPACT
A33: Peak Month Revenue (July est) | B33: ='Sunflow Seasonality'!H34 -> 169500
A34: Low Month Revenue (Feb est) | B34: ='Sunflow Seasonality'!C34 -> 116700
A35: Annual Revenue (with seasonality) | B35: ='Sunflow Seasonality'!N34 -> 1475225

Sheet Assumptions
A1: ASSUMPTIONS & INPUTS
A2: Blue values are inputs you can change
A4: REVENUE
A6: Current Monthly Revenue | B6: 95000 | C6: From existing clients
A7: Target Monthly Revenue | B7: 150000
A8: Pending Deal Revenue (Monthly) | B8: 25000 | C8: Two deals closing in 30 days
A9: Average New Client Size | B9: 15000 | C9: Target: $10K-$20K/month
A11: Peddle Monthly | B11: 49000
A12: Wrensilva Monthly | B12: 14000
A13: Alo Monthly | B13: 10000
A14: Sonsie Monthly | B14: 9000
A15: Kaspar & Lugay Monthly | B15: 6000
A16: Sunflow Monthly | B16: 5500
A17: Other/New Clients | B17: 1500
A19: LABOR COSTS
A21: Maya Monthly (Salary + Benefits) | B21: 3600 | C21: $3K salary + $600 health ins
A22: Santi Monthly | B22: 2500 | C22: Full-time
A23: Leah Monthly | B23: 200 | C23: 1-2 hrs/month
A24: Contract Labor Monthly (Current) | B24: 28000 | C24: Tracy + active contractors
A26: Account Manager Hired? | B26: No | C26: Change to Yes when hired
A27: Account Manager Annual Salary | B27: 100000 | C27: Range: $80K-$150K
A28: AM Payroll Burden (Benefits/Taxes) | B28: 0.15
A29: Project Manager Hired? | B29: No | C29: Change to Yes when hired
A30: Project Manager Annual Salary | B30: 70000 | C30: Range: $60K-$80K
A31: PM Payroll Burden | B31: 0.15
A33: OPERATING EXPENSES
A35: Software/Tools Monthly | B35: 4000
A36: Insurance Monthly | B36: 3000
A37: Accounting Monthly | B37: 2000
A38: Other Operating Monthly | B38: 1500
A40: TARGETS
A42: Target Operating Margin | B42: 0.35
A43: Revenue to Hire AM | B43: 110000 | C43: Hire when revenue hits this
A44: Revenue to Hire PM | B44: 120000

Sheet Projection
A1: 12-MONTH GROWTH PROJECTION
B3: Current | C3: Month 1 | D3: Month 2 | E3: Month 3 | F3: Month 4 | G3: Month 5 | H3: Month 6 | I3: Month 7 | J3: Month 8 | K3: Month 9 | L3: Month 10 | M3: Month 11 | N3: Month 12
A4: REVENUE
A5: Base Client Revenue | B5: =Assumptions!B6 -> 95000 | C5: =B5 -> 95000 | D5: =C5 -> 95000 | E5: =D5 -> 95000 | F5: =E5 -> 95000 | G5: =F5 -> 95000 | H5: =G5 -> 95000 | I5: =H5 -> 95000 | J5: =I5 -> 95000 | ... N5: =M5 -> 95000
A6: New Deal Revenue (Pending) | B6: 0 | C6: =Assumptions!B8 -> 25000 | D6: =C6 -> 25000 | E6: =D6 -> 25000 | F6: =E6 -> 25000 | G6: =F6 -> 25000 | H6: =G6 -> 25000 | I6: =H6 -> 25000 | J6: =I6 -> 25000 | K6: =J6 -> 25000 | ... N6: =M6 -> 25000
A7: Total Monthly Revenue | B7: =SUM(B5:B6) -> 95000 | C7: =SUM(C5:C6) -> 120000 | D7: =SUM(D5:D6) -> 120000 | E7: =SUM(E5:E6) -> 120000 | F7: =SUM(F5:F6) -> 120000 | G7: =SUM(G5:G6) -> 120000 | H7: =SUM(H5:H6) -> 120000 | I7: =SUM(I5:I6) -> 120000 | ... N7: =SUM(N5:N6) -> 120000
A8: EXPENSES
A9: Core Team (Maya + Santi + Leah) | B9: =Assumptions!B21+Assumptions!B22+Assumptions!B23 -> 6300 | C9: =Assumptions!B21+Assumptions!B22+Assumptions!B23 -> 6300 | D9: =Assumptions!B21+Assumptions!B22+Assumptions!B23 -> 6300 | E9: =Assumptions!B21+Assumptions!B22+Assumptions!B23 -> 6300 | F9: =Assumptions!B21+Assumptions!B22+Assumptions!B23 -> 6300 | G9: =Assumptions!B21+Assumptions!B22+Assumptions!B23 -> 6300 | H9: =Assumptions!B21+Assumptions!B22+Assumptions!B23 -> 6300 | I9: =Assumptions!B21+Assumptions!B22+Assumptions!B23 -> 6300 | J9: =Assumptions!B21+Assumptions!B22+Assumptions!B23 -> 6300 | K9: =Assumptions!B21+Assumptions!B22+Assumptions!B23 -> 6300 | L9: =Assumptions!B21+Assumptions!B22+Assumptions!B23 -> 6300 | M9: =Assumptions!B21+Assumptions!B22+Assumptions!B23 -> 6300 | N9: =Assumptions!B21+Assumptions!B22+Assumptions!B23 -> 6300
A10: Contract Labor | B10: =Assumptions!B24 -> 28000 | C10: =Assumptions!B24 -> 28000 | D10: =Assumptions!B24 -> 28000 | E10: =Assumptions!B24 -> 28000 | F10: =Assumptions!B24 -> 28000 | G10: =Assumptions!B24 -> 28000 | H10: =Assumptions!B24 -> 28000 | I10: =Assumptions!B24 -> 28000 | J10: =Assumptions!B24 -> 28000 | K10: =Assumptions!B24 -> 28000 | L10: =Assumptions!B24 -> 28000 | M10: =Assumptions!B24 -> 28000 | N10: =Assumptions!B24 -> 28000
A11: Account Manager (if hired) | B11: =IF(Assumptions!B26="Yes",(Assumptions!B27*(1+Assumptions!B28))/12,0) -> 0 | C11: =IF(Assumptions!B26="Yes",(Assumptions!B27*(1+Assumptions!B28))/12,0) -> 0 | D11: =IF(Assumptions!B26="Yes",(Assumptions!B27*(1+Assumptions!B28))/12,0) -> 0 | E11: =IF(Assumptions!B26="Yes",(Assumptions!B27*(1+Assumptions!B28))/12,0) -> 0 | F11: =IF(Assumptions!B26="Yes",(Assumptions!B27*(1+Assumptions!B28))/12,0) -> 0 | G11: =IF(Assumptions!B26="Yes",(Assumptions!B27*(1+Assumptions!B28))/12,0) -> 0 | H11: =IF(Assumptions!B26="Yes",(Assumptions!B27*(1+Assumptions!B28))/12,0) -> 0 | I11: =IF(Assumptions!B26="Yes",(Assumptions!B27*(1+Assumptions!B28))/12,0) -> 0 | J11: =IF(Assumptions!B26="Yes",(Assumptions!B27*(1+Assumptions!B28))/12,0) -> 0 | K11: =IF(Assumptions!B26="Yes",(Assumptions!B27*(1+Assumptions!B28))/12,0) -> 0 | L11: =IF(Assumptions!B26="Yes",(Assumptions!B27*(1+Assumptions!B28))/12,0) -> 0 | M11: =IF(Assumptions!B26="Yes",(Assumptions!B27*(1+Assumptions!B28))/12,0) -> 0 | N11: =IF(Assumptions!B26="Yes",(Assumptions!B27*(1+Assumptions!B28))/12,0) -> 0
A12: Project Manager (if hired) | B12: =IF(Assumptions!B29="Yes",(Assumptions!B30*(1+Assumptions!B31))/12,0) -> 0 | C12: =IF(Assumptions!B29="Yes",(Assumptions!B30*(1+Assumptions!B31))/12,0) -> 0 | D12: =IF(Assumptions!B29="Yes",(Assumptions!B30*(1+Assumptions!B31))/12,0) -> 0 | E12: =IF(Assumptions!B29="Yes",(Assumptions!B30*(1+Assumptions!B31))/12,0) -> 0 | F12: =IF(Assumptions!B29="Yes",(Assumptions!B30*(1+Assumptions!B31))/12,0) -> 0 | G12: =IF(Assumptions!B29="Yes",(Assumptions!B30*(1+Assumptions!B31))/12,0) -> 0 | H12: =IF(Assumptions!B29="Yes",(Assumptions!B30*(1+Assumptions!B31))/12,0) -> 0 | I12: =IF(Assumptions!B29="Yes",(Assumptions!B30*(1+Assumptions!B31))/12,0) -> 0 | J12: =IF(Assumptions!B29="Yes",(Assumptions!B30*(1+Assumptions!B31))/12,0) -> 0 | K12: =IF(Assumptions!B29="Yes",(Assumptions!B30*(1+Assumptions!B31))/12,0) -> 0 | L12: =IF(Assumptions!B29="Yes",(Assumptions!B30*(1+Assumptions!B31))/12,0) -> 0 | M12: =IF(Assumptions!B29="Yes",(Assumptions!B30*(1+Assumptions!B31))/12,0) -> 0 | N12: =IF(Assumptions!B29="Yes",(Assumptions!B30*(1+Assumptions!B31))/12,0) -> 0
A13: Software & Tools | B13: =Assumptions!B35 -> 4000 | C13: =Assumptions!B35 -> 4000 | D13: =Assumptions!B35 -> 4000 | E13: =Assumptions!B35 -> 4000 | F13: =Assumptions!B35 -> 4000 | G13: =Assumptions!B35 -> 4000 | H13: =Assumptions!B35 -> 4000 | I13: =Assumptions!B35 -> 4000 | J13: =Assumptions!B35 -> 4000 | K13: =Assumptions!B35 -> 4000 | L13: =Assumptions!B35 -> 4000 | M13: =Assumptions!B35 -> 4000 | N13: =Assumptions!B35 -> 4000
A14: Insurance | B14: =Assumptions!B36 -> 3000 | C14: =Assumptions!B36 -> 3000 | D14: =Assumptions!B36 -> 3000 | E14: =Assumptions!B36 -> 3000 | F14: =Assumptions!B36 -> 3000 | G14: =Assumptions!B36 -> 3000 | H14: =Assumptions!B36 -> 3000 | I14: =Assumptions!B36 -> 3000 | J14: =Assumptions!B36 -> 3000 | K14: =Assumptions!B36 -> 3000 | L14: =Assumptions!B36 -> 3000 | M14: =Assumptions!B36 -> 3000 | N14: =Assumptions!B36 -> 3000
A15: Accounting | B15: =Assumptions!B37 -> 2000 | C15: =Assumptions!B37 -> 2000 | D15: =Assumptions!B37 -> 2000 | E15: =Assumptions!B37 -> 2000 | F15: =Assumptions!B37 -> 2000 | G15: =Assumptions!B37 -> 2000 | H15: =Assumptions!B37 -> 2000 | I15: =Assumptions!B37 -> 2000 | J15: =Assumptions!B37 -> 2000 | K15: =Assumptions!B37 -> 2000 | L15: =Assumptions!B37 -> 2000 | M15: =Assumptions!B37 -> 2000 | N15: =Assumptions!B37 -> 2000
A16: Other Operating | B16: =Assumptions!B38 -> 1500 | C16: =Assumptions!B38 -> 1500 | D16: =Assumptions!B38 -> 1500 | E16: =Assumptions!B38 -> 1500 | F16: =Assumptions!B38 -> 1500 | G16: =Assumptions!B38 -> 1500 | H16: =Assumptions!B38 -> 1500 | I16: =Assumptions!B38 -> 1500 | J16: =Assumptions!B38 -> 1500 | K16: =Assumptions!B38 -> 1500 | L16: =Assumptions!B38 -> 1500 | M16: =Assumptions!B38 -> 1500 | N16: =Assumptions!B38 -> 1500
A17: Total Expenses | B17: =SUM(B9:B16) -> 44800 | C17: =SUM(C9:C16) -> 44800 | D17: =SUM(D9:D16) -> 44800 | E17: =SUM(E9:E16) -> 44800 | F17: =SUM(F9:F16) -> 44800 | G17: =SUM(G9:G16) -> 44800 | H17: =SUM(H9:H16) -> 44800 | I17: =SUM(I9:I16) -> 44800 | ... N17: =SUM(N9:N16) -> 44800
A18: PROFITABILITY
A19: Net Operating Income | B19: =B7-B17 -> 50200 | C19: =C7-C17 -> 75200 | D19: =D7-D17 -> 75200 | E19: =E7-E17 -> 75200 | F19: =F7-F17 -> 75200 | G19: =G7-G17 -> 75200 | H19: =H7-H17 -> 75200 | I19: =I7-I17 -> 75200 | ... N19: =N7-N17 -> 75200
A20: Operating Margin | B20: =IF(B7>0,B19/B7,0) -> 0.52842105 | C20: =IF(C7>0,C19/C7,0) -> 0.62666667 | D20: =IF(D7>0,D19/D7,0) -> 0.62666667 | E20: =IF(E7>0,E19/E7,0) -> 0.62666667 | F20: =IF(F7>0,F19/F7,0) -> 0.62666667 | G20: =IF(G7>0,G19/G7,0) -> 0.62666667 | H20: =IF(H7>0,H19/H7,0) -> 0.62666667 | I20: =IF(I7>0,I19/I7,0) -> 0.62666667 | ... N20: =IF(N7>0,N19/N7,0) -> 0.62666667
A22: HIRING TRIGGERS
A23: Revenue >= $110K (Hire AM)? | B23: =IF(B7>=Assumptions!B43,"YES","NO") -> NO | C23: =IF(C7>=Assumptions!B43,"YES","NO") -> YES | D23: =IF(D7>=Assumptions!B43,"YES","NO") -> YES | E23: =IF(E7>=Assumptions!B43,"YES","NO") -> YES | F23: =IF(F7>=Assumptions!B43,"YES","NO") -> YES | G23: =IF(G7>=Assumptions!B43,"YES","NO") -> YES | H23: =IF(H7>=Assumptions!B43,"YES","NO") -> YES | I23: =IF(I7>=Assumptions!B43,"YES","NO") -> YES | J23: =IF(J7>=Assumptions!B43,"YES","NO") -> YES | K23: =IF(K7>=Assumptions!B43,"YES","NO") -> YES | L23: =IF(L7>=Assumptions!B43,"YES","NO") -> YES | M23: =IF(M7>=Assumptions!B43,"YES","NO") -> YES | N23: =IF(N7>=Assumptions!B43,"YES","NO") -> YES
A24: Revenue >= $120K (Hire PM)? | B24: =IF(B7>=Assumptions!B44,"YES","NO") -> NO | C24: =IF(C7>=Assumptions!B44,"YES","NO") -> YES | D24: =IF(D7>=Assumptions!B44,"YES","NO") -> YES | E24: =IF(E7>=Assumptions!B44,"YES","NO") -> YES | F24: =IF(F7>=Assumptions!B44,"YES","NO") -> YES | G24: =IF(G7>=Assumptions!B44,"YES","NO") -> YES | H24: =IF(H7>=Assumptions!B44,"YES","NO") -> YES | I24: =IF(I7>=Assumptions!B44,"YES","NO") -> YES | J24: =IF(J7>=Assumptions!B44,"YES","NO") -> YES | K24: =IF(K7>=Assumptions!B44,"YES","NO") -> YES | L24: =IF(L7>=Assumptions!B44,"YES","NO") -> YES | M24: =IF(M7>=Assumptions!B44,"YES","NO") -> YES | N24: =IF(N7>=Assumptions!B44,"YES","NO") -> YES
A25: Margin >= Target? | B25: =IF(B20>=Assumptions!B42,"YES","NO") -> YES | C25: =IF(C20>=Assumptions!B42,"YES","NO") -> YES | D25: =IF(D20>=Assumptions!B42,"YES","NO") -> YES | E25: =IF(E20>=Assumptions!B42,"YES","NO") -> YES | F25: =IF(F20>=Assumptions!B42,"YES","NO") -> YES | G25: =IF(G20>=Assumptions!B42,"YES","NO") -> YES | H25: =IF(H20>=Assumptions!B42,"YES","NO") -> YES | I25: =IF(I20>=Assumptions!B42,"YES","NO") -> YES | J25: =IF(J20>=Assumptions!B42,"YES","NO") -> YES | K25: =IF(K20>=Assumptions!B42,"YES","NO") -> YES | L25: =IF(L20>=Assumptions!B42,"YES","NO") -> YES | M25: =IF(M20>=Assumptions!B42,"YES","NO") -> YES | N25: =IF(N20>=Assumptions!B42,"YES","NO") -> YES

Sheet Team Costs
A1: TEAM & CONTRACTOR COSTS
A3: Name | B3: Role | C3: Type | D3: Monthly Cost | E3: Annual Cost | F3: Notes
A4: CORE TEAM
A5: Maya Kumits | B5: Operations | C5: Full-Time | D5: 3600 | E5: =D5*12 -> 43200 | F5: $3K salary + $600 health insurance
A6: Santiago Garcia Dietze | B6: Media/Operations | C6: Full-Time | D6: 2500 | E6: =D6*12 -> 30000 | F6: Now full-time
A7: Leah Peters | B7: Support | C7: Contractor | D7: 200 | E7: =D7*12 -> 2400 | F7: 1-2 hrs/month
A9: ACTIVE CONTRACTORS
A10: Tracy/Worksource Mgmt | B10: Admin/Coordination | C10: Contractor | D10: 5000 | E10: =D10*12 -> 60000
A11: Camila Escobar | B11: TBD | C11: Contractor | D11: 4000 | E11: =D11*12 -> 48000
A12: Lisel Arroyo | B12: TBD | C12: Contractor | D12: 4500 | E12: =D12*12 -> 54000
A13: George Poradek | B13: TBD | C13: Contractor | D13: 1500 | E13: =D13*12 -> 18000
A14: Other Active Contractors | B14: Various | C14: Contractor | D14: 13000 | E14: =D14*12 -> 156000 | F14: Update with actual breakdown
A16: PLANNED HIRES
A17: Account Manager | B17: Client Relationships | C17: Full-Time | D17: =Assumptions!B27/12 -> 8333.3333 | E17: =Assumptions!B27 -> 100000 | F17: Hire when revenue >= $110K/mo
A18: Project Manager | B18: Delivery/Operations | C18: Full-Time | D18: =Assumptions!B30/12 -> 5833.3333 | E18: =Assumptions!B30 -> 70000 | F18: Hire when revenue >= $120K/mo
A20: TOTALS
A21: Current Core Team | D21: =SUM(D5:D7) -> 6300 | E21: =D21*12 -> 75600
A22: Current Contractors | D22: =SUM(D10:D14) -> 28000 | E22: =D22*12 -> 336000
A23: Total Current Labor | D23: =D21+D22 -> 34300 | E23: =D23*12 -> 411600
A24: Planned Hires (Annual) | E24: =E17+E18 -> 170000

Sheet Bonus Structure
A1: QUARTERLY BONUS FRAMEWORK
A2: Review and distribute quarterly based on company performance and individual contribution
A4: BONUS PHILOSOPHY
A6: Bonus Pool = 10% of Quarterly Net Operating Income above target margin
A7: Only paid when quarterly margin exceeds 30%
A8: Distributed based on role weight and individual performance score
A10: QUARTERLY INPUTS
A12: Quarter Revenue | B12: 285000 | C12: Enter actual quarterly revenue
A13: Quarter Expenses | B13: 170000
A14: Quarter NOI | B14: =B12-B13 -> 115000
A15: Quarter Margin | B15: =IF(B12>0,B14/B12,0) -> 0.40350877
A16: Margin Threshold for Bonus | B16: 0.3
A17: Bonus Pool % | B17: 0.1
A18: Eligible for Bonus? | B18: =IF(B15>=B16,"YES","NO") -> YES
A19: Total Bonus Pool | B19: =IF(B18="YES",B14*B17,0) -> 11500
A21: BONUS DISTRIBUTION
A23: Team Member | B23: Role Weight | C23: Performance (1-5) | D23: Weighted Score | E23: Bonus Amount
A24: Maya Kumits | B24: 2 | C24: 4 | D24: =B24*C24 -> 8 | E24: =IF($B$19>0,($B$19*D24)/SUM($D$24:$D$28),0) -> 5411.7647
A25: Santiago Garcia Dietze | B25: 1.5 | C25: 4 | D25: =B25*C25 -> 6 | E25: =IF($B$19>0,($B$19*D25)/SUM($D$24:$D$28),0) -> 4058.8235
A26: Account Manager (if hired) | B26: 2.5 | C26: 0 | D26: =B26*C26 -> 0 | E26: =IF($B$19>0,($B$19*D26)/SUM($D$24:$D$28),0) -> 0 | F26: Set score to 0 if not hired
A27: Project Manager (if hired) | B27: 2 | C27: 0 | D27: =B27*C27 -> 0 | E27: =IF($B$19>0,($B$19*D27)/SUM($D$24:$D$28),0) -> 0
A28: Contractor Pool | B28: 1 | C28: 3 | D28: =B28*C28 -> 3 | E28: =IF($B$19>0,($B$19*D28)/SUM($D$24:$D$28),0) -> 2029.4118 | F28: Distribute among active contractors
A29: TOTAL | D29: =SUM(D24:D28) -> 17 | E29: =SUM(E24:E28) -> 11500
A31: QUARTERLY REVIEW PROCESS
A33: 1. Close the quarter books by day 5 of new quarter
A34: 2. Calculate quarterly revenue, expenses, and margin
A35: 3. If margin >= 30%, calculate bonus pool (10% of NOI)
A36: 4. Rate each team member 1-5 on performance
A37: 5. Calculate weighted distribution
A38: 6. Communicate and pay bonuses by day 15 of new quarter

Sheet Monthly Tracker
A1: MONTHLY PERFORMANCE TRACKER
A2: Update this sheet at the end of each month to compare actuals vs budget
A3: Month: | B3: February 2026
A4: Metric | B4: Budget | C4: Actual | D4: Variance | E4: Variance % | F4: Notes
A5: REVENUE
A6: Total Revenue | B6: 95000 | C6: 0 | D6: =C6-B6 -> -95000 | E6: =IF(B6>0,D6/B6,0) -> -1
A8: EXPENSES
A9: Core Team | B9: 6300 | C9: 0 | D9: =C9-B9 -> -6300 | E9: =IF(B9>0,D9/B9,0) -> -1
A10: Contract Labor | B10: 28000 | C10: 0 | D10: =C10-B10 -> -28000 | E10: =IF(B10>0,D10/B10,0) -> -1
A11: Account Manager | B11: 0 | C11: 0 | D11: =C11-B11 -> 0 | E11: =IF(B11>0,D11/B11,0) -> 0
A12: Project Manager | B12: 0 | C12: 0 | D12: =C12-B12 -> 0 | E12: =IF(B12>0,D12/B12,0) -> 0
A13: Software/Tools | B13: 4000 | C13: 0 | D13: =C13-B13 -> -4000 | E13: =IF(B13>0,D13/B13,0) -> -1
A14: Insurance | B14: 3000 | C14: 0 | D14: =C14-B14 -> -3000 | E14: =IF(B14>0,D14/B14,0) -> -1
A15: Accounting | B15: 2000 | C15: 0 | D15: =C15-B15 -> -2000 | E15: =IF(B15>0,D15/B15,0) -> -1
A16: Other Operating | B16: 1500 | C16: 0 | D16: =C16-B16 -> -1500 | E16: =IF(B16>0,D16/B16,0) -> -1
A17: Total Expenses | B17: =SUM(B9:B16) -> 44800 | C17: =SUM(C9:C16) -> 0 | D17: =C17-B17 -> -44800 | E17: =IF(B17>0,D17/B17,0) -> -1
A19: PROFITABILITY
A20: Net Operating Income | B20: =B6-B17 -> 50200 | C20: =C6-C17 -> 0 | D20: =C20-B20 -> -50200 | E20: =IF(B20<>0,D20/ABS(B20),0) -> -1
A21: Operating Margin | B21: =IF(B6>0,B20/B6,0) -> 0.52842105 | C21: =IF(C6>0,C20/C6,0) -> 0 | D21: =C21-B21 -> -0.52842105

Sheet Sunflow Seasonality
A1: SUNFLOW SEASONAL REVENUE MODEL
A2: Based on 2025 actuals - Peak Mar-Aug, Low Sep-Feb
A4: 2025 ACTUALS
B5: Jan | C5: Feb | D5: Mar | E5: Apr | F5: May | G5: Jun | H5: Jul | I5: Aug | J5: Sep | K5: Oct | L5: Nov | M5: Dec | N5: Total
A6: Sunflow 2025 | B6: 3900 | C6: 2400 | D6: 3900 | E6: 6600 | F6: 6900 | G6: 0 | H6: 55000 | I6: 17100 | J6: 8800 | K6: 2600 | L6: 2300 | M6: 6300 | N6: =SUM(B6:M6) -> 115800
A8: 2026 PROJECTIONS
A9: Baseline Monthly | B9: 5500 | C9: (Current retainer assumption)
A10: Seasonal Multiplier | B10: 0.7 | C10: 0.4 | D10: 0.7 | E10: 1.2 | F10: 1.25 | G10: 2 | H10: 10 | I10: 3.1 | J10: 1.6 | K10: 0.5 | L10: 0.4 | M10: 1.1
A11: Projected 2026 | B11: =$B$9*B10 -> 3850 | C11: =$B$9*C10 -> 2200 | D11: =$B$9*D10 -> 3850 | E11: =$B$9*E10 -> 6600 | F11: =$B$9*F10 -> 6875 | G11: =$B$9*G10 -> 11000 | H11: =$B$9*H10 -> 55000 | I11: =$B$9*I10 -> 17050 | ... M11: =$B$9*M10 -> 6050 | N11: =SUM(B11:M11) -> 126225
A13: IMPACT ON TOTAL REVENUE
A15: Base Revenue (excl Sunflow) | B15: 89500 | C15: ($95K total - $5.5K Sunflow avg)
A16: Sunflow Avg (with seasonality) | B16: =N11/12 -> 10518.75
A17: Avg Monthly Revenue | B17: =B15+B16 -> 100018.75
A19: Peak Month (July) | B19: =B15+H11 -> 144500
A20: Low Month (Feb/Nov) | B20: =B15+MIN(B11:M11) -> 91700
A22: 2026 MONTHLY REVENUE BY CLIENT (with Sunflow Seasonality)
B23: Jan | C23: Feb | D23: Mar | E23: Apr | F23: May | G23: Jun | H23: Jul | I23: Aug | J23: Sep | K23: Oct | L23: Nov | M23: Dec | N23: Total
A24: Peddle | B24: 49000 | C24: 49000 | D24: 49000 | E24: 49000 | F24: 49000 | G24: 49000 | H24: 49000 | I24: 49000 | J24: 49000 | K24: 49000 | L24: 49000 | M24: 49000 | N24: =SUM(B24:M24) -> 588000
A25: Wrensilva | B25: 14000 | C25: 14000 | D25: 14000 | E25: 14000 | F25: 14000 | G25: 14000 | H25: 14000 | I25: 14000 | J25: 14000 | K25: 14000 | L25: 14000 | M25: 14000 | N25: =SUM(B25:M25) -> 168000
A26: Alo | B26: 10000 | C26: 10000 | D26: 10000 | E26: 10000 | F26: 10000 | G26: 10000 | H26: 10000 | I26: 10000 | J26: 10000 | K26: 10000 | L26: 10000 | M26: 10000 | N26: =SUM(B26:M26) -> 120000
A27: Sonsie | B27: 9000 | C27: 9000 | D27: 9000 | E27: 9000 | F27: 9000 | G27: 9000 | H27: 9000 | I27: 9000 | J27: 9000 | K27: 9000 | L27: 9000 | M27: 9000 | N27: =SUM(B27:M27) -> 108000
A28: Kaspar & Lugay | B28: 6000 | C28: 6000 | D28: 6000 | E28: 6000 | F28: 6000 | G28: 6000 | H28: 6000 | I28: 6000 | J28: 6000 | K28: 6000 | L28: 6000 | M28: 6000 | N28: =SUM(B28:M28) -> 72000
A29: Sunflow (Seasonal) | B29: =B11 -> 3850 | C29: =C11 -> 2200 | D29: =D11 -> 3850 | E29: =E11 -> 6600 | F29: =F11 -> 6875 | G29: =G11 -> 11000 | H29: =H11 -> 55000 | I29: =I11 -> 17050 | ... M29: =M11 -> 6050 | N29: =SUM(B29:M29) -> 126225
A30: Other/Buffer | B30: 1500 | C30: 1500 | D30: 1500 | E30: 1500 | F30: 1500 | G30: 1500 | H30: 1500 | I30: 1500 | J30: 1500 | K30: 1500 | L30: 1500 | M30: 1500 | N30: =SUM(B30:M30) -> 18000
A31: TOTAL MONTHLY REVENUE | B31: =SUM(B24:B30) -> 93350 | C31: =SUM(C24:C30) -> 91700 | D31: =SUM(D24:D30) -> 93350 | E31: =SUM(E24:E30) -> 96100 | F31: =SUM(F24:F30) -> 96375 | G31: =SUM(G24:G30) -> 100500 | H31: =SUM(H24:H30) -> 144500 | I31: =SUM(I24:I30) -> 106550 | ... M31: =SUM(M24:M30) -> 95550 | N31: =SUM(B31:M31) -> 1200225
A33: New Deals (Pending) | B33: 0 | C33: =Assumptions!B8 -> 25000 | D33: =Assumptions!B8 -> 25000 | E33: =Assumptions!B8 -> 25000 | F33: =Assumptions!B8 -> 25000 | G33: =Assumptions!B8 -> 25000 | H33: =Assumptions!B8 -> 25000 | I33: =Assumptions!B8 -> 25000 | J33: =Assumptions!B8 -> 25000 | K33: =Assumptions!B8 -> 25000 | L33: =Assumptions!B8 -> 25000 | M33: =Assumptions!B8 -> 25000
A34: TOTAL WITH NEW DEALS | B34: =B31+B33 -> 93350 | C34: =C31+C33 -> 116700 | D34: =D31+D33 -> 118350 | E34: =E31+E33 -> 121100 | F34: =F31+F33 -> 121375 | G34: =G31+G33 -> 125500 | H34: =H31+H33 -> 169500 | I34: =I31+I33 -> 131550 | ... M34: =M31+M33 -> 120550 | N34: =SUM(B34:M34) -> 1475225
